Workbook

Sheet Inputs
A1: IFRS 9 Amortization Template
A3: Source | B3: User-provide | D3: Learning note: • Blue cells = user inputs. • Black cells = formulas. • The workbook uses a standard amortization formula. • Change the yellow input cells to build your own scenarios.
A4: Loan amount | B4: 5000
A5: Annual interest rate | B5: 0.04
A6: Term (years) | B6: 1
A7: Payments per year | B7: 12
A8: Start date | B8: 43436
A9: Extra payment in Month 1 | B9: 100
A10: Monthly rate | B10: =B5/B7 -> 0.0033333333
A11: Total number of periods | B11: =B6*B7 -> 12
A12: Scheduled payment (EMI) | B12: =ROUND(B4*B10*(1+B10)^B11/((1+B10)^B11-1),2) -> 425.75
A13: Approx. total scheduled payments | B13: =ROUND(B12*B11,2) -> 5109

Sheet Amortization
A1: Amortization Schedule
A3: Loan amount | B3: =Inputs!B4 -> 5000
A4: Annual rate | B4: =Inputs!B5 -> 0.04
A5: Term (years) | B5: =Inputs!B6 -> 1
A6: Payments/year | B6: =Inputs!B7 -> 12
A7: Monthly rate | B7: =Inputs!B10 -> 0.0033333333
A8: Scheduled EMI | B8: =Inputs!B12 -> 425.75
A9: Extra payment (Month 1) | B9: =Inputs!B9 -> 100
A12: Period | B12: Payment Date | C12: Beginning Balance | D12: Scheduled EMI | E12: Extra Payment | F12: Total Payment | G12: Interest | H12: Principal | I12: Ending Balance
A13: 1 | B13: 43436 | C13: =Inputs!B4 -> 5000 | D13: =Inputs!B12 -> 425.75 | E13: =Inputs!B9 -> 100 | F13: =D13+E13 -> 525.75 | G13: =C13*$B$7 -> 16.666667 | H13: =F13-G13 -> 509.08333 | I13: =C13-H13 -> 4490.9167
A14: 2 | B14: 43467 | C14: =I13 -> 4490.9167 | D14: =Inputs!B12 -> 425.75 | E14: 0 | F14: =D14+E14 -> 425.75 | G14: =C14*$B$7 -> 14.969722 | H14: =F14-G14 -> 410.78028 | I14: =C14-H14 -> 4080.1364
A15: 3 | B15: 43498 | C15: =I14 -> 4080.1364 | D15: =Inputs!B12 -> 425.75 | E15: 0 | F15: =D15+E15 -> 425.75 | G15: =C15*$B$7 -> 13.600455 | H15: =F15-G15 -> 412.14955 | I15: =C15-H15 -> 3667.9868
A16: 4 | B16: 43526 | C16: =I15 -> 3667.9868 | D16: =Inputs!B12 -> 425.75 | E16: 0 | F16: =D16+E16 -> 425.75 | G16: =C16*$B$7 -> 12.226623 | H16: =F16-G16 -> 413.52338 | I16: =C16-H16 -> 3254.4635
A17: 5 | B17: 43557 | C17: =I16 -> 3254.4635 | D17: =Inputs!B12 -> 425.75 | E17: 0 | F17: =D17+E17 -> 425.75 | G17: =C17*$B$7 -> 10.848212 | H17: =F17-G17 -> 414.90179 | I17: =C17-H17 -> 2839.5617
A18: 6 | B18: 43587 | C18: =I17 -> 2839.5617 | D18: =Inputs!B12 -> 425.75 | E18: 0 | F18: =D18+E18 -> 425.75 | G18: =C18*$B$7 -> 9.4652056 | H18: =F18-G18 -> 416.28479 | I18: =C18-H18 -> 2423.2769
A19: 7 | B19: 43618 | C19: =I18 -> 2423.2769 | D19: =Inputs!B12 -> 425.75 | E19: 0 | F19: =D19+E19 -> 425.75 | G19: =C19*$B$7 -> 8.0775896 | H19: =F19-G19 -> 417.67241 | I19: =C19-H19 -> 2005.6045
A20: 8 | B20: 43648 | C20: =I19 -> 2005.6045 | D20: =Inputs!B12 -> 425.75 | E20: 0 | F20: =D20+E20 -> 425.75 | G20: =C20*$B$7 -> 6.6853482 | H20: =F20-G20 -> 419.06465 | I20: =C20-H20 -> 1586.5398
A21: 9 | B21: 43679 | C21: =I20 -> 1586.5398 | D21: =Inputs!B12 -> 425.75 | E21: 0 | F21: =D21+E21 -> 425.75 | G21: =C21*$B$7 -> 5.2884661 | H21: =F21-G21 -> 420.46153 | I21: =C21-H21 -> 1166.0783
A22: 10 | B22: 43710 | C22: =I21 -> 1166.0783 | D22: =Inputs!B12 -> 425.75 | E22: 0 | F22: =D22+E22 -> 425.75 | G22: =C22*$B$7 -> 3.8869276 | H22: =F22-G22 -> 421.86307 | I22: =C22-H22 -> 744.21522
A23: 11 | B23: 43740 | C23: =I22 -> 744.21522 | D23: =Inputs!B12 -> 425.75 | E23: 0 | F23: =D23+E23 -> 425.75 | G23: =C23*$B$7 -> 2.4807174 | H23: =F23-G23 -> 423.26928 | I23: =C23-H23 -> 320.94593
A24: 12 | B24: 43771 | C24: =I23 -> 320.94593 | D24: =Inputs!B12 -> 425.75 | E24: 0 | F24: =D24+E24 -> 425.75 | G24: =C24*$B$7 -> 1.0698198 | H24: =F24-G24 -> 424.68018 | I24: =C24-H24 -> -103.73425
A27: Summary
A28: Total scheduled payments | B28: =SUM(D13:D24) -> 5109
A29: Total extra payments | B29: =SUM(E13:E24) -> 100
A30: Total interest paid | B30: =SUM(G13:G24) -> 105.26575
A31: Ending balance after 12 months | B31: =I24 -> -103.73425
A32: Balloon / payoff amount needed to close the loan | B32: =I24 -> -103.73425
A34: Interpretation | B34: If the ending balance is negative, the extra payment has overpaid the loan. In real banking, the final installment would usually be capped at the exact payoff amount.
